dfcleanan/__init__.py
dfcleanan/cleandf.py
dfcleanan-0.1.6.dist-info/licenses/LICENSE
dfcleanan-0.1.6.dist-info/METADATA
dfcleanan-0.1.6.dist-info/WHEEL
dfcleanan-0.1.6.dist-info/top_level.txt
dfcleanan-0.1.6.dist-info/RECORD
