Metadata-Version: 2.4
Name: dfcleanan
Version: 0.1.6
Summary: A Python package to clean NaN values in pandas DataFrames
Home-page: https://github.com/QurbonovAI
Author: Ozodbek Qurbonov
Author-email: qurbonovo2008@gmail.com
License: MIT
Classifier: Programming Language :: Python :: 3
Classifier: License :: OSI Approved :: MIT License
Classifier: Operating System :: OS Independent
Requires-Python: >=3.8
License-File: LICENSE
Requires-Dist: pandas>=2.3.2
Dynamic: author
Dynamic: author-email
Dynamic: classifier
Dynamic: description
Dynamic: description-content-type
Dynamic: home-page
Dynamic: license
Dynamic: license-file
Dynamic: requires-dist
Dynamic: requires-python
Dynamic: summary
